{
  "index": {
    "title": "Home",
    "theme": {
      "breadcrumb": false,
      "footer": false,
      "sidebar": false,
      "toc": false,
      "pagination": false,
      "layout": "article"
    }
  },
  "--": {
    "type": "separator"
  },
  "docs": {
    "title": "Docs",
    "type": "page"
  },
  "examples": {
    "title": "Examples",
    "type": "page"
  },
  "about": {
    "title": "About",
    "type": "page"
  },
  "contact": {
    "title": "What is IIIF? ↗",
    "type": "page",
    "href": "https://iiif.io/",
    "newWindow": true
  }
}
